Libraray/__init__.py
Libraray/age.py
mo_adly-0.0.2.dist-info/licenses/LICENSE.txt
mo_adly-0.0.2.dist-info/METADATA
mo_adly-0.0.2.dist-info/WHEEL
mo_adly-0.0.2.dist-info/top_level.txt
mo_adly-0.0.2.dist-info/RECORD
